first_setup/__init__.py
first_setup/admin.py
first_setup/apps.py
first_setup/db.py
first_setup/decorators.py
first_setup/models.py
first_setup/tests.py
first_setup/urls.py
first_setup/version.py
first_setup/views.py
first_setup/migrations/__init__.py
first_setup/templates/base.html
first_setup/templates/setup/db.html
first_setup/templates/setup/error.html
first_setup/templates/setup/initial.html
first_setup/templates/setup/welcome.html
django_initial_setup-0.0.9.dist-info/LICENSE
django_initial_setup-0.0.9.dist-info/METADATA
django_initial_setup-0.0.9.dist-info/WHEEL
django_initial_setup-0.0.9.dist-info/top_level.txt
django_initial_setup-0.0.9.dist-info/RECORD
