Metadata-Version: 2.1
Name: django-initial-setup
Version: 0.0.9
Summary: Django Initial Setup provides inital setup screen developed with Django for first launch.
Home-page: https://github.com/shotastage/django-initial-setup
Author: Shota Shimazu
Author-email: hornet.live.mf@gmail.com
License: MIT
Download-URL: https://pypi.python.org/pypi/django-initial-setup
Platform: UNKNOWN
Classifier: Framework :: Django
Classifier: Framework :: Django :: 3.0
Classifier: Framework :: Django :: 3.1
Classifier: License :: OSI Approved :: MIT License
Classifier: Operating System :: OS Independent
Classifier: Programming Language :: Python :: 3.7
Classifier: Programming Language :: Python :: 3.8
Classifier: Programming Language :: Python :: 3.9
Classifier: Topic :: Security
Classifier: Topic :: System :: Systems Administration :: Authentication/Directory
Requires-Dist: django (>=3.0)
